sirtep/__init__.py
sirtep/optimization.py
sirtep/sirtep_dataclasses/__init__.py
sirtep/sirtep_dataclasses/scheduler_dataclasses.py
sirtep-0.2.1.dist-info/licenses/LICENSE.txt
sirtep-0.2.1.dist-info/METADATA
sirtep-0.2.1.dist-info/WHEEL
sirtep-0.2.1.dist-info/RECORD
