Metadata-Version: 2.4
Name: sirtep
Version: 0.2.1
Summary: Tiny library for construction scheduling based on spatial data with additional attributes.
License: BSD-3-Clause
License-File: LICENSE.txt
Author: Leon
Author-email: turkov.leon-2@yandex.ru
Requires-Python: >=3.11,<4.0
Classifier: License :: OSI Approved :: BSD License
Classifier: Programming Language :: Python :: 3
Classifier: Programming Language :: Python :: 3.11
Classifier: Programming Language :: Python :: 3.12
Classifier: Programming Language :: Python :: 3.13
Classifier: Programming Language :: Python :: 3.14
Requires-Dist: cvxpy (>=1.7.0)
Requires-Dist: geopandas (>=1.0.1)
Requires-Dist: highspy (>=1.11.0)
Requires-Dist: loguru (>=0.7.3)
Requires-Dist: pandas (>=2.2.0)
Requires-Dist: tqdm (>=4.66.2)
